labtool_ex2/LatexPrinter.py
labtool_ex2/__init__.py
labtool_ex2/dtype.py
labtool_ex2/helpers.py
labtool_ex2/monkeypatch_uncertainties.py
labtool_ex2/printer.py
labtool_ex2/project.py
labtool_ex2/symbol.py
labtool_ex2/uarray.py
labtool_ex2-0.0.3.dist-info/LICENSE
labtool_ex2-0.0.3.dist-info/METADATA
labtool_ex2-0.0.3.dist-info/WHEEL
labtool_ex2-0.0.3.dist-info/top_level.txt
labtool_ex2-0.0.3.dist-info/RECORD
